toko/__init__.py
toko/cache.py
toko/cli.py
toko/config.py
toko/cost.py
toko/counter.py
toko/data/__init__.py
toko/data/openrouter_models.json
toko/file_reader.py
toko/formatters.py
toko/models.py
toko/price_update.py
toko-0.2.1.dist-info/WHEEL
toko-0.2.1.dist-info/entry_points.txt
toko-0.2.1.dist-info/METADATA
toko-0.2.1.dist-info/RECORD
