Metadata-Version: 2.3
Name: toko
Version: 0.2.1
Summary: A token counting cli tool and package
Author: Hugh Wimberly
Author-email: Hugh Wimberly <hugh.wimberly@gmail.com>
Requires-Dist: genai-prices>=0.0.48
Requires-Dist: httpx>=0.28.1
Requires-Dist: pathspec>=0.12.1
Requires-Dist: rich>=14.2.0
Requires-Dist: tiktoken>=0.12.0
Requires-Dist: typer>=0.20.0
Requires-Dist: mistral-common[sentencepiece]>=1.8.5 ; extra == 'all'
Requires-Dist: transformers>=4.57.1 ; extra == 'all'
Requires-Dist: mistral-common[sentencepiece]>=1.8.5 ; extra == 'mistral'
Requires-Dist: transformers>=4.57.1 ; extra == 'transformers'
Requires-Python: >=3.14
Provides-Extra: all
Provides-Extra: mistral
Provides-Extra: transformers
